asreview/__init__.py
asreview/__main__.py
asreview/_deprecated.py
asreview/_version.py
asreview/datasets.py
asreview/extensions.py
asreview/learner.py
asreview/metrics.py
asreview/utils.py
asreview/data/__init__.py
asreview/data/base.py
asreview/data/loader.py
asreview/data/record.py
asreview/data/ris.py
asreview/data/search.py
asreview/data/store.py
asreview/data/tabular.py
asreview/data/utils.py
asreview/models/__init__.py
asreview/models/_metadata.py
asreview/models/balancers.py
asreview/models/classifiers.py
asreview/models/cli.py
asreview/models/feature_extractors.py
asreview/models/mixin.py
asreview/models/models.py
asreview/models/queriers.py
asreview/models/stoppers.py
asreview/project/__init__.py
asreview/project/api.py
asreview/project/exceptions.py
asreview/project/migrate.py
asreview/project/schema.py
asreview/simulation/__init__.py
asreview/simulation/cli.py
asreview/simulation/simulate.py
asreview/state/__init__.py
asreview/state/contextmanager.py
asreview/state/sqlstate.py
asreview/webapp/.env.development
asreview/webapp/.env.production
asreview/webapp/.prettierignore
asreview/webapp/.prettierrc
asreview/webapp/__init__.py
asreview/webapp/_tasks.py
asreview/webapp/app.py
asreview/webapp/help.json
asreview/webapp/jsconfig.json
asreview/webapp/package-lock.json
asreview/webapp/package.json
asreview/webapp/utils.py
asreview/webapp/.husky/pre-commit
asreview/webapp/_api/__init__.py
asreview/webapp/_api/admin.py
asreview/webapp/_api/auth.py
asreview/webapp/_api/projects.py
asreview/webapp/_api/team.py
asreview/webapp/_api/utils.py
asreview/webapp/_authentication/__init__.py
asreview/webapp/_authentication/decorators.py
asreview/webapp/_authentication/models.py
asreview/webapp/_authentication/oauth_handler.py
asreview/webapp/_authentication/remote_user_handler.py
asreview/webapp/_authentication/utils.py
asreview/webapp/_entry_points/__init__.py
asreview/webapp/_entry_points/auth_tool.py
asreview/webapp/_entry_points/lab.py
asreview-2.1.1.dist-info/licenses/LICENSE
asreview-2.1.1.dist-info/METADATA
asreview-2.1.1.dist-info/WHEEL
asreview-2.1.1.dist-info/entry_points.txt
asreview-2.1.1.dist-info/top_level.txt
asreview-2.1.1.dist-info/RECORD
