Metadata-Version: 2.4
Name: asreview
Version: 2.1.1
Summary: ASReview LAB - A tool for AI-assisted systematic reviews
Author-email: ASReview LAB developers <asreview@uu.nl>
License-Expression: Apache-2.0
Project-URL: Bug Tracker, https://github.com/asreview/asreview/issues
Project-URL: Documentation, https://asreview.readthedocs.io/en/stable//
Project-URL: Downloads, https://github.com/asreview/asreview/releases
Project-URL: Homepage, https://asreview.ai/
Project-URL: Release Notes, https://github.com/asreview/asreview/releases
Project-URL: Slack Chat, https://asreviewcommunity.slack.com
Project-URL: Source Code, https://github.com/asreview/asreview
Project-URL: YouTube, https://www.youtube.com/@ASReview
Keywords: systematic review,machine-learning
Classifier: Development Status :: 5 - Production/Stable
Classifier: Programming Language :: Python :: 3
Classifier: Programming Language :: Python :: 3.10
Classifier: Programming Language :: Python :: 3.11
Classifier: Programming Language :: Python :: 3.12
Classifier: Programming Language :: Python :: 3.13
Classifier: Topic :: Scientific/Engineering :: Artificial Intelligence
Classifier: Topic :: Scientific/Engineering :: Information Analysis
Classifier: Topic :: Text Processing :: General
Classifier: Framework :: Flask
Requires-Python: >=3.10
License-File: LICENSE
Requires-Dist: numpy
Requires-Dist: pandas<3,>=2.2
Requires-Dist: scikit-learn>=1.5
Requires-Dist: rispy~=0.9.0
Requires-Dist: flask>=2.3.0
Requires-Dist: flask_cors
Requires-Dist: flask-login>=0.6.3
Requires-Dist: flask-mail
Requires-Dist: Werkzeug>=2.3.2
Requires-Dist: openpyxl>=3.0.3
Requires-Dist: jsonschema
Requires-Dist: filelock
Requires-Dist: Flask-SQLAlchemy>=3.0.2
Requires-Dist: requests
Requires-Dist: tqdm
Requires-Dist: rich
Requires-Dist: waitress
Requires-Dist: gevent>=20
Requires-Dist: datahugger>=0.2
Requires-Dist: synergy_dataset
Requires-Dist: sqlalchemy-utils
Requires-Dist: tomli; python_version < "3.11"
Provides-Extra: lint
Requires-Dist: ruff; extra == "lint"
Requires-Dist: check-manifest; extra == "lint"
Provides-Extra: test
Requires-Dist: coverage; extra == "test"
Requires-Dist: pytest; extra == "test"
Requires-Dist: pytest-random-order; extra == "test"
Requires-Dist: pytest-selenium; extra == "test"
Provides-Extra: docs
Requires-Dist: ipython; extra == "docs"
Requires-Dist: sphinx; extra == "docs"
Requires-Dist: pydata-sphinx-theme; extra == "docs"
Requires-Dist: sphinx-reredirects; extra == "docs"
Requires-Dist: sphinxcontrib-youtube; extra == "docs"
Requires-Dist: nbsphinx; extra == "docs"
Requires-Dist: sphinx-design; extra == "docs"
Requires-Dist: myst-parser; extra == "docs"
Provides-Extra: dev
Requires-Dist: setuptools; extra == "dev"
Requires-Dist: asreview[lint]; extra == "dev"
Requires-Dist: asreview[test]; extra == "dev"
Requires-Dist: asreview[docs]; extra == "dev"
Dynamic: license-file
